Shh/__init__.py
pyShhX-1.0.1.dist-info/LICENSE
pyShhX-1.0.1.dist-info/METADATA
pyShhX-1.0.1.dist-info/WHEEL
pyShhX-1.0.1.dist-info/top_level.txt
pyShhX-1.0.1.dist-info/RECORD
